faker_pandas/__init__.py
faker_pandas/provider.py
faker_pandas-0.1.2.dist-info/WHEEL
faker_pandas-0.1.2.dist-info/METADATA
faker_pandas-0.1.2.dist-info/RECORD
