Metadata-Version: 2.1
Name: faker-pandas
Version: 0.1.2
Summary: Adds Provider for Faker library to Generate randomized Pandas DataFrames
Home-page: https://github.com/nitori/faker_pandas
License: MIT
Author: Sani
Author-email: sani@sani.love
Requires-Python: >=3.9,<4.0
Classifier: License :: OSI Approved :: MIT License
Classifier: Programming Language :: Python :: 3
Classifier: Programming Language :: Python :: 3.10
Classifier: Programming Language :: Python :: 3.9
Requires-Dist: Faker (>=13.6.0,<14.0.0)
Requires-Dist: pandas (>=1.4.2,<2.0.0)
Project-URL: Repository, https://github.com/nitori/faker_pandas
Project-URL: issues, https://github.com/nitori/faker_pandas/issues
